CHANGELOG.md
LICENSE
MANIFEST.in
README.rst
ez_setup.py
setup.py
arcovid19/__init__.py
arcovid19/cache.py
arcovid19/cases.py
arcovid19/cli.py
arcovid19/core.py
arcovid19/models.py
arcovid19.egg-info/PKG-INFO
arcovid19.egg-info/SOURCES.txt
arcovid19.egg-info/dependency_links.txt
arcovid19.egg-info/entry_points.txt
arcovid19.egg-info/requires.txt
arcovid19.egg-info/top_level.txt
arcovid19/web/__init__.py
arcovid19/web/bp.py
arcovid19/web/forms.py
arcovid19/web/static/arcovid19.css
arcovid19/web/static/arcovid19.js
arcovid19/web/static/favicon.ico
arcovid19/web/static/logo.png
arcovid19/web/static/logo.xcf
arcovid19/web/static/logos.png
arcovid19/web/templates/InfectionCurve.html
arcovid19/web/templates/base.html
arcovid19/web/translations/es/LC_MESSAGES/messages.mo
arcovid19/web/translations/es/LC_MESSAGES/messages.po