Metadata-Version: 1.1
Name: arcovid19
Version: 0.5.1
Summary: Utilities to access different Argentina-Related databases of COVID-19 data from the IATE task force.
Home-page: https://github.com/ivco19/libs
Author: IATE COVID-19 Task Force
Author-email: jbc.develop@gmail.com
License: BSD-3
Keywords: covid-19,project,datasets,argentina
Platform: UNKNOWN
Classifier: Development Status :: 4 - Beta
Classifier: Intended Audience :: Science/Research
Classifier: License :: OSI Approved :: BSD License
Classifier: Operating System :: OS Independent
Classifier: Programming Language :: Python
Classifier: Programming Language :: Python :: 3.7
Classifier: Programming Language :: Python :: Implementation :: CPython
Classifier: Topic :: Scientific/Engineering
